pyklout.py
setup.py
test_klout.py
pyklout.egg-info/PKG-INFO
pyklout.egg-info/SOURCES.txt
pyklout.egg-info/dependency_links.txt
pyklout.egg-info/top_level.txt