Metadata-Version: 1.0
Name: pyklout
Version: 0.2
Summary: Python Wrapper for Klout (http://klout.com/) API
Home-page: https://github.com/marcelcaraciolo/PyKlout
Author: Marcel Caraciolo
Author-email: caraciol@gmail.com
License: LGPL3
Download-URL: https://github.com/marcelcaraciolo/PyKlout/tarball/master
Keywords: klout api
Platform: UNKNOWN
Classifier: Development Status :: 4 - Beta
Classifier: Topic :: Utilities
Classifier: License :: OSI Approved :: GNU Library or Lesser General Public License (LGPL)
Classifier: Natural Language :: English
Classifier: Operating System :: OS Independent
Classifier: Programming Language :: Python :: 2
Classifier: Topic :: Internet
Classifier: Topic :: Internet :: WWW/HTTP
